report_vp/__init__.py
report_vp/report.py
report_vp-0.0.6.dist-info/METADATA
report_vp-0.0.6.dist-info/WHEEL
report_vp-0.0.6.dist-info/RECORD
