Metadata-Version: 2.1
Name: report_vp
Version: 0.0.6
Summary: A report generation package for results of Monaco 2018 Racing
Project-URL: Homepage, https://git.foxminded.ua/volodymyr-perehuda-nyc/task-6-report-of-monaco-2018-racing
Project-URL: Issues, https://git.foxminded.ua/volodymyr-perehuda-nyc/task-6-report-of-monaco-2018-racing/issues
Author-email: Volodymyr Perehuda <author@example.com>
Classifier: License :: OSI Approved :: MIT License
Classifier: Operating System :: OS Independent
Classifier: Programming Language :: Python :: 3.11
Requires-Python: >=3.11.4
